[
  {
    "producto_id": 1,
    "nombre": "NVidia GeForce Aorus RTX 3090",
    "imagen": "NVIDIA-GEFORCE-AORUS-RTX-3090-MASTER.jpg",
    "descripcion": "Placa de video NVidia GeForce Aorus RTX 3090 con memoria GDDR6 de 8Gb, 14 Gbps y resolución hasta 4K.",
    "precio": 302680,
    "tipo": "video",
    "marca": "NVidia",
    "memoria_g": "GDDR6",
    "memoria": "8GB",
    "ventas": 10
  },
  {
    "producto_id": 2,
    "nombre": "AMD Radeon Rx 5600 xt ASUS",
    "imagen": "AMD-RADEON-RX-5600-XT-ASUS-DUAL.jpg",
    "descripcion": "Placa de video AMD Radeon Rx 5600 xt ASUS con memoria GDDR6 de 6Gb, 12 Gbps y resolución hasta 4K.",
    "precio": 39468,
    "tipo": "video",
    "marca": "AMD",
    "memoria_g": "GDDR6",
    "memoria": "6GB",
    "ventas": 10
  },
  {
    "producto_id": 3,
    "nombre": "AMD Radeon Rx 5700 xt Gigabyte",
    "imagen": "AMD-RADEON-RX-5700-XT-GIGABYTE-GAMING.jpg",
    "descripcion": "Placa de video AMD Radeon Rx 5700 xt Gigabyte con memoria GDDR6 de 6Gb, 14 Gbps y resolución hasta 4K.",
    "precio": 59791,
    "tipo": "video",
    "marca": "AMD",
    "memoria_g": "GDDR6",
    "memoria": "6GB",
    "ventas": 0
  },
  {
    "producto_id": 4,
    "nombre": "AMD Radeon Rx 5700 xt MSI Mech",
    "imagen": "AMD-RADEON-RX-5700-XT-MSI-MECH.jpg",
    "descripcion": "Placa de video AMD Radeon Rx 5700 xt MSI Mech con memoria GDDR6 de 6Gb, 14 Gbps y resolución hasta 4K.",
    "precio": 56948,
    "tipo": "video",
    "marca": "AMD",
    "memoria_g": "GDDR6",
    "memoria": "6GB",
    "ventas": 0
  },
  {
    "producto_id": 5,
    "nombre": "AMD Radeon Rx 5700 xt Sapphire",
    "imagen": "AMD-RADEON-RX-5700-XT-SAPPHIRE-PULSE.jpg",
    "descripcion": "Placa de video AMD Radeon Rx 5700 xt Sapphire con memoria GDDR6 de 8Gb, 14 Gbps y resolución hasta 4K.",
    "precio": 61639,
    "tipo": "video",
    "marca": "AMD",
    "memoria_g": "GDDR6",
    "memoria": "8GB",
    "ventas": 0
  },
  {
    "producto_id": 6,
    "nombre": "NVidia GeForce RTX 3070 XLR8",
    "imagen": "NVIDIA-GEFORCE-RTX-3070-XLR8-REVEL-GAMING.jpg",
    "descripcion": "Placa de video NVidia GeForce RTX 3070 XLR8 con memoria GDDR6 de 8Gb, 14 Gbps y resolución hasta 4K.",
    "precio": 100280,
    "tipo": "video",
    "marca": "NVidia",
    "memoria_g": "GDDR6",
    "memoria": "8GB",
    "ventas": 0
  },
  {
    "producto_id": 7,
    "nombre": "Procesador AMD Ryzen 5 5600x",
    "imagen": "PROCESADOR-AMD-RYZEN-5-5600x.jpg",
    "descripcion": "Procesador AMD Ryzen 5 5600x con 6 núcleos y memoria DDR4 de hasta 3200mHz de velocidad.",
    "precio": 35695,
    "tipo": "procesadores",
    "marca": "AMD",
    "memoria_g": "DDR4",
    "nucleos": 6,
    "ventas": 10
  },
  {
    "producto_id": 8,
    "nombre": "Procesador AMD Ryzen 7 5800x",
    "imagen": "PROCESADOR-AMD-RYZEN-7-5800.jpg",
    "descripcion": "Procesador AMD Ryzen 7 5800x con 8 núcleos y memoria DDR4 de hasta 3200mHz de velocidad.",
    "precio": 56115,
    "tipo": "procesadores",
    "memoria_g": "DDR4",
    "nucleos": 8,
    "marca": "AMD",
    "ventas": 10
  },
  {
    "producto_id": 9,
    "nombre": "Procesador AMD Ryzen 9 3950x",
    "imagen": "PROCESADOR-AMD-RYZEN-9-3950x.jpg",
    "descripcion": "Procesador AMD Ryzen 9 3950x con 16 núcleos y memoria DDR4 de hasta 3200mHz de velocidad.",
    "precio": 88688,
    "tipo": "procesadores",
    "memoria_g": "DDR4",
    "nucleos": 16,
    "marca": "AMD",
    "ventas": 0
  },
  {
    "producto_id": 10,
    "nombre": "Procesador Intel Core I7 10700f",
    "imagen": "PROCESADOR-INTEL-CORE-I7-10700f.jpg",
    "descripcion": "Procesador Intel Core I7 10700f con 8 núcleos y memoria DDR4 de hasta 2900mHz de velocidad.",
    "precio": 38639,
    "tipo": "procesadores",
    "memoria_g": "DDR4",
    "nucleos": 8,
    "marca": "Intel",
    "ventas": 0
  },
  {
    "producto_id": 11,
    "nombre": "Procesador Intel Core I9 10850K",
    "imagen": "PROCESADOR-INTEL-CORE-I9-10850K.jpg",
    "descripcion": "Procesador Intel Core I9 10850K con 10 núcleos y memoria DDR4 de hasta 3600mHz de velocidad.",
    "precio": 56580,
    "tipo": "procesadores",
    "memoria_g": "DDR4",
    "nucleos": 10,
    "marca": "Intel",
    "ventas": 0
  },
  {
    "producto_id": 12,
    "nombre": "Procesador Intel Pentium Gold",
    "imagen": "PROCESADOR-INTEL-PENTIUM-GOLD-G5420.jpg",
    "descripcion": "Procesador Intel Pentium Gold con 2 núcleos y memoria DDR4 de hasta 2300mHz de velocidad.",
    "precio": 6439,
    "tipo": "procesadores",
    "memoria_g": "DDR4",
    "nucleos": 2,
    "marca": "Intel",
    "ventas": 0
  },
  {
    "producto_id": 13,
    "nombre": "Memoria DDR4 16Gb Corsair Airflow Red",
    "imagen": "MEMORIA-DDR4-16GB-CORSAIR-AIRFLOW-RED.jpg",
    "descripcion": "Memoria RAM Corsair Airflow Red DDR4 de 16Gb y 4266MHZ.",
    "precio": 26680,
    "tipo": "ram",
    "memoria_g": "DDR4",
    "memoria": "16GB",
    "marca": "Corsair",
    "ventas": 10
  },
  {
    "producto_id": 14,
    "nombre": "Memoria DDR4 16Gb Corsair Dominator",
    "imagen": "MEMORIA-DDR4-16GB-CORSAIR-DOMINATOR.jpg",
    "descripcion": "Memoria RAM Corsair Dominator DDR4 de 16Gb y 4000MHZ.",
    "precio": 34959,
    "tipo": "ram",
    "memoria_g": "DDR4",
    "memoria": "16GB",
    "marca": "Corsair",
    "ventas": 10
  },
  {
    "producto_id": 15,
    "nombre": "Memoria DDR4 16Gb Aorus Dual Channel",
    "imagen": "MEMORIA-DDR4-16GB-DUAL-CHANNEL-AORUS.jpg",
    "descripcion": "Memoria RAM Aorus Dual Channel DDR4 de 16Gb y 4400MHZ.",
    "precio": 22079,
    "tipo": "ram",
    "memoria_g": "DDR4",
    "memoria": "16GB",
    "marca": "Aorus",
    "ventas": 0
  },
  {
    "producto_id": 16,
    "nombre": "Memoria DDR4 16Gb Aorus Gigabyte",
    "imagen": "MEMORIA-DDR4-16GB-GIGABYTE-AORUS.jpg",
    "descripcion": "Memoria RAM Aorus Gigabyte DDR4 de 16Gb y 3600MHZ.",
    "precio": 16559,
    "tipo": "ram",
    "memoria_g": "DDR4",
    "memoria": "16GB",
    "marca": "Aorus",
    "ventas": 0
  },
  {
    "producto_id": 17,
    "nombre": "Memoria DDR4 16Gb HyperX Fury Gamer",
    "imagen": "MEMORIA-DDR4-16GB-HYPERX-FURY-GAMER.jpg",
    "descripcion": "Memoria RAM HyperX Fury Gamer DDR4 de 16Gb y 3200MHZ.",
    "precio": 8739,
    "tipo": "ram",
    "memoria_g": "DDR4",
    "memoria": "16GB",
    "marca": "HyperX",
    "ventas": 0
  },
  {
    "producto_id": 18,
    "nombre": "Memoria DDR4 16Gb Corsair Vengeance",
    "imagen": "MEMORIA-DDR4-32GB-CORSAIR-VENGEANCE.jpg",
    "descripcion": "Memoria RAM Corsair Vengeance DDR4 de 16Gb y 3600MHZ.",
    "precio": 16559,
    "tipo": "ram",
    "memoria_g": "DDR4",
    "memoria": "16GB",
    "marca": "Corsair",
    "ventas": 0
  },
  {
    "producto_id": 19,
    "nombre": "Motherboard Asus RoG Strix B550E B550",
    "imagen": "MOTHERBOARD-ASUS-ROG-STRIX-B550E-B550.jpg",
    "descripcion": "Motherboard Asus para serie Ryzen 3°Gen, RAM DDR4 de 128GB y AMD B550.",
    "precio": 31555,
    "tipo": "motherboard",
    "memoria_g": "DDR4",
    "memoria": "128GB",
    "marca": "Asus",
    "ventas": 10
  },
  {
    "producto_id": 20,
    "nombre": "Motherboard Asus Crosshair VIII Hero",
    "imagen": "MOTHERBOARD-ASUS-ROG-STRIX-CROSSHAIR-VIII.jpg",
    "descripcion": "Motherboard Asus para serie Ryzen 4°Gen, RAM DDR4 de 128GB y AMD X570.",
    "precio": 47380,
    "tipo": "motherboard",
    "memoria_g": "DDR4",
    "memoria": "128GB",
    "marca": "Asus",
    "ventas": 10
  },
  {
    "producto_id": 21,
    "nombre": "Motherboard Gigabyte B550 Aorus Pro AMD",
    "imagen": "MOTHERBOARD-GIGABYTE-B550-AORUS-PRO.jpg",
    "descripcion": "Motherboard Gigabyte para serie Ryzen 3°Gen, RAM DDR4 de 128GB y AMD B550.",
    "precio": 29439,
    "tipo": "motherboard",
    "memoria_g": "DDR4",
    "memoria": "128GB",
    "marca": "Aorus",
    "ventas": 0
  },
  {
    "producto_id": 22,
    "nombre": "Motherboard Gigabyte B550 Vision D AMD",
    "imagen": "MOTHERBOARD-GIGABYTE-B550-VISION-D-AMD.jpg",
    "descripcion": "Motherboard Gigabyte para serie Ryzen 3°Gen, RAM DDR4 de 128GB y AMD B550.",
    "precio": 36799,
    "tipo": "motherboard",
    "memoria_g": "DDR4",
    "memoria": "128GB",
    "marca": "AMD",
    "ventas": 0
  },
  {
    "producto_id": 23,
    "nombre": "Motherboard Gigabyte GA Z490 Aorus Pro AX",
    "imagen": "MOTHERBOARD-GIGABYTE-GA-Z490-AORUS-PRO.jpg",
    "descripcion": "Motherboard Gigabyte para serie Intel I9, RAM DDR4 de 128GB y Intel Z490.",
    "precio": 33303,
    "tipo": "motherboard",
    "memoria_g": "DDR4",
    "memoria": "128GB",
    "marca": "Aorus",
    "ventas": 0
  },
  {
    "producto_id": 24,
    "nombre": "Motherboard Gigabyte X570 Aorus Ultra",
    "imagen": "MOTHERBOARD-GIGABYTE-X570-AORUS-ULTRA.jpg",
    "descripcion": "Motherboard Gigabyte para serie Ryzen 3°Gen, RAM DDR4 de 128GB y AMD X570.",
    "precio": 41400,
    "tipo": "motherboard",
    "memoria_g": "DDR4",
    "memoria": "128GB",
    "marca": "Aorus",
    "ventas": 0
  }
]